thermopro_ble/__init__.py
thermopro_ble/device.py
thermopro_ble/parser.py
thermopro_ble/py.typed
thermopro_ble-1.1.2.dist-info/METADATA
thermopro_ble-1.1.2.dist-info/WHEEL
thermopro_ble-1.1.2.dist-info/licenses/LICENSE
thermopro_ble-1.1.2.dist-info/RECORD
