Metadata-Version: 2.4
Name: thermopro-ble
Version: 1.1.2
Summary: Thermopro BLE Sensors
License: MIT
License-File: LICENSE
Author: J. Nick Koston
Author-email: nick@koston.org
Requires-Python: >=3.11,<4
Classifier: Development Status :: 2 - Pre-Alpha
Classifier: Intended Audience :: Developers
Classifier: License :: OSI Approved :: MIT License
Classifier: Natural Language :: English
Classifier: Operating System :: OS Independent
Classifier: Programming Language :: Python :: 3
Classifier: Programming Language :: Python :: 3.11
Classifier: Programming Language :: Python :: 3.12
Classifier: Programming Language :: Python :: 3.13
Classifier: Programming Language :: Python :: 3.14
Classifier: Topic :: Software Development :: Libraries
Provides-Extra: docs
Requires-Dist: Sphinx (>=5,<9) ; extra == "docs"
Requires-Dist: bleak (>=0.21.1) ; python_version >= "3.10" and python_version < "3.14"
Requires-Dist: bluetooth-data-tools (>=1.28.0)
Requires-Dist: bluetooth-sensor-state-data (>=1.8.0)
Requires-Dist: habluetooth (>=3.42.0) ; python_version >= "3.11" and python_version < "3.14"
Requires-Dist: myst-parser (>=0.18,<4.1) ; extra == "docs"
Requires-Dist: sensor-state-data (>=2.0.2) ; python_version >= "3.11" and python_version < "4"
Requires-Dist: sphinx-rtd-theme (>=1,<4) ; extra == "docs"
Project-URL: Bug Tracker, https://github.com/bluetooth-devices/thermopro-ble/issues
Project-URL: Changelog, https://github.com/bluetooth-devices/thermopro-ble/blob/main/CHANGELOG.md
Project-URL: Documentation, https://thermopro-ble.readthedocs.io
Project-URL: Repository, https://github.com/bluetooth-devices/thermopro-ble
